github_codeowners/__init__.py
github_codeowners/cli.py
github_codeowners/models.py
github_codeowners/parser.py
github_codeowners/writer.py
github_codeowners-0.1.0.dist-info/licenses/LICENSE
github_codeowners-0.1.0.dist-info/METADATA
github_codeowners-0.1.0.dist-info/WHEEL
github_codeowners-0.1.0.dist-info/entry_points.txt
github_codeowners-0.1.0.dist-info/top_level.txt
github_codeowners-0.1.0.dist-info/RECORD
