Metadata-Version: 2.4
Name: github-codeowners
Version: 0.1.0
Summary: A Python library and CLI for parsing and managing GitHub CODEOWNERS files
Author-email: Henry Upton <henryupton@gmail.com>
License: MIT
Requires-Python: >=3.8
License-File: LICENSE
Requires-Dist: click>=8.0.0
Provides-Extra: dev
Requires-Dist: pytest>=7.0.0; extra == "dev"
Requires-Dist: black>=22.0.0; extra == "dev"
Requires-Dist: mypy>=0.990; extra == "dev"
Dynamic: license-file
